winrt/Microsoft.WindowsAppRuntime.Bootstrap.dll
winrt/_winrt_microsoft_windows_applicationmodel_dynamicdependency_bootstrap.cp310-win32.pyd
winrt/_winrt_microsoft_windows_applicationmodel_dynamicdependency_bootstrap.pyi
winrt/microsoft/windows/applicationmodel/dynamicdependency/bootstrap/__init__.py
winrt/microsoft/windows/applicationmodel/dynamicdependency/bootstrap/py.typed
winrt_Microsoft.Windows.ApplicationModel.DynamicDependency.Bootstrap-2.3.0.dist-info/METADATA
winrt_Microsoft.Windows.ApplicationModel.DynamicDependency.Bootstrap-2.3.0.dist-info/WHEEL
winrt_Microsoft.Windows.ApplicationModel.DynamicDependency.Bootstrap-2.3.0.dist-info/top_level.txt
winrt_Microsoft.Windows.ApplicationModel.DynamicDependency.Bootstrap-2.3.0.dist-info/RECORD
